gamecreator/__init__.py
gamecreator/engine.py
gamecreator-1.0.0.dist-info/METADATA
gamecreator-1.0.0.dist-info/WHEEL
gamecreator-1.0.0.dist-info/top_level.txt
gamecreator-1.0.0.dist-info/RECORD
