Metadata-Version: 2.1
Name: gamecreator
Version: 1.0.0
Summary: python game creator using pygame but simple
Home-page: UNKNOWN
Author: icarogamer2001
Author-email: deiamota050@gmail.com
License: UNKNOWN
Platform: UNKNOWN
Requires-Python: >=3.6
